{
"variants":{
"connected=0,orientation=0":{"model":"mdeco:poleBlackIron0","x":270,"y":90},
"connected=1,orientation=0":{"model":"mdeco:poleBlackIron1","x":270,"y":90},
"connected=2,orientation=0":{"model":"mdeco:poleBlackIron2","x":270,"y":90},
"connected=3,orientation=0":{"model":"mdeco:poleBlackIron3","x":270,"y":90},
"connected=0,orientation=1":{"model":"mdeco:poleBlackIron0"},
"connected=1,orientation=1":{"model":"mdeco:poleBlackIron1"},
"connected=2,orientation=1":{"model":"mdeco:poleBlackIron2"},
"connected=3,orientation=1":{"model":"mdeco:poleBlackIron3"},
"connected=0,orientation=2":{"model":"mdeco:poleBlackIron0","x":270},
"connected=1,orientation=2":{"model":"mdeco:poleBlackIron1","x":270,"y":180},
"connected=2,orientation=2":{"model":"mdeco:poleBlackIron2","x":270,"y":180},
"connected=3,orientation=2":{"model":"mdeco:poleBlackIron3","x":270}
}
}
